mwtypes/__init__.py
mwtypes/about.py
mwtypes/errors.py
mwtypes/log_item.py
mwtypes/namespace.py
mwtypes/page.py
mwtypes/revision.py
mwtypes/slots.py
mwtypes/string_type.py
mwtypes/timestamp.py
mwtypes/upload.py
mwtypes/user.py
mwtypes/util.py
mwtypes/files/__init__.py
mwtypes/files/functions.py
mwtypes/files/p7z.py
mwtypes/files/tests/__init__.py
mwtypes/files/tests/test_functions.py
mwtypes/files/tests/test_p7z.py
mwtypes/tests/__init__.py
mwtypes/tests/test_log_item.py
mwtypes/tests/test_namespace.py
mwtypes/tests/test_revision.py
mwtypes/tests/test_string_type.py
mwtypes/tests/test_timestamp.py
mwtypes/tests/test_upload.py
mwtypes/tests/test_user.py
mwtypes-0.4.0.dist-info/LICENSE
mwtypes-0.4.0.dist-info/METADATA
mwtypes-0.4.0.dist-info/WHEEL
mwtypes-0.4.0.dist-info/top_level.txt
mwtypes-0.4.0.dist-info/RECORD
